decision_tree_rules_extractor/__init__.py
decision_tree_rules_extractor/extractor.py
decision_tree_rules_extractor/process.py
decision_tree_rules_extractor-0.1.2.dist-info/LICENSE
decision_tree_rules_extractor-0.1.2.dist-info/METADATA
decision_tree_rules_extractor-0.1.2.dist-info/WHEEL
decision_tree_rules_extractor-0.1.2.dist-info/entry_points.txt
decision_tree_rules_extractor-0.1.2.dist-info/RECORD
